zuto/__init__.py
zuto/group.py
zuto/i.py
zuto/logger.py
zuto/model.py
zuto/runner.py
zuto/utils.py
zuto/groups/builtin.py
zuto/groups/ext.py
zuto-0.2.2.dist-info/METADATA
zuto-0.2.2.dist-info/WHEEL
zuto-0.2.2.dist-info/licenses/LICENSE
zuto-0.2.2.dist-info/RECORD
