Metadata-Version: 2.3
Name: zuto
Version: 0.2.2
Summary: personal windows automator
Author-email: ZackaryW <gitzackw@gmail.com>
License-File: LICENSE
Requires-Python: >=3.8
Requires-Dist: pygetwindow>=0.0.9
Requires-Dist: python-dotenv>=1.0.1
Requires-Dist: pyyaml>=6.0.2
Requires-Dist: requests>=2.32.3
Requires-Dist: toml>=0.10.2
Requires-Dist: zuu==0.1.12
